pydoro/__init__.py
pydoro/pydoro_tui.py
pydoro/pydoro_core/__init__.py
pydoro/pydoro_core/b15.wav
pydoro/pydoro_core/config.py
pydoro/pydoro_core/sound.py
pydoro/pydoro_core/tomato.py
pydoro/pydoro_core/util.py
pydoro-0.2.3.dist-info/LICENSE
pydoro-0.2.3.dist-info/METADATA
pydoro-0.2.3.dist-info/WHEEL
pydoro-0.2.3.dist-info/entry_points.txt
pydoro-0.2.3.dist-info/top_level.txt
pydoro-0.2.3.dist-info/RECORD
