Metadata-Version: 2.1
Name: pydoro
Version: 0.2.3
Summary: Terminal Pomodoro Timer
Home-page: https://github.com/JaDogg/pydoro
Author: Bhathiya Perera
Author-email: jadogg.coder@gmail.com
License: MIT
Keywords: tomato pomodoro pydoro timer work
Platform: UNKNOWN
Classifier: Development Status :: 3 - Alpha
Classifier: Intended Audience :: Information Technology
Classifier: License :: OSI Approved :: MIT License
Classifier: Programming Language :: Python :: 3.6
Classifier: Programming Language :: Python :: 3.7
Classifier: Programming Language :: Python :: 3.8
Requires-Python: >=3.6
License-File: LICENSE
Requires-Dist: prompt-toolkit (>=3.0.3)
Provides-Extra: audio
Requires-Dist: pyobjc-core (>=5.2) ; (platform_system=="Darwin") and extra == 'audio'
Requires-Dist: pyobjc-framework-Cocoa (>=5.2) ; (platform_system=="Darwin") and extra == 'audio'
Requires-Dist: pycairo (>=1.18.1) ; (platform_system=="Linux") and extra == 'audio'
Requires-Dist: PyGObject (>=3.32.1) ; (platform_system=="Linux") and extra == 'audio'
